LICENSE
MANIFEST.in
README.md
setup.py
ethrpc_keys/__init__.py
ethrpc_keys/constants.py
ethrpc_keys/datatypes.py
ethrpc_keys/exceptions.py
ethrpc_keys/main.py
ethrpc_keys/py.typed
ethrpc_keys/validation.py
ethrpc_keys.egg-info/PKG-INFO
ethrpc_keys.egg-info/SOURCES.txt
ethrpc_keys.egg-info/dependency_links.txt
ethrpc_keys.egg-info/not-zip-safe
ethrpc_keys.egg-info/requires.txt
ethrpc_keys.egg-info/top_level.txt
ethrpc_keys/backends/__init__.py
ethrpc_keys/backends/base.py
ethrpc_keys/backends/coincurve.py
ethrpc_keys/backends/native/__init__.py
ethrpc_keys/backends/native/ecdsa.py
ethrpc_keys/backends/native/jacobian.py
ethrpc_keys/backends/native/main.py
ethrpc_keys/tools/__init__.py
ethrpc_keys/tools/factories.py
ethrpc_keys/utils/__init__.py
ethrpc_keys/utils/address.py
ethrpc_keys/utils/der.py
ethrpc_keys/utils/module_loading.py
ethrpc_keys/utils/numeric.py
ethrpc_keys/utils/padding.py