Metadata-Version: 2.1
Name: ethrpc-keys
Version: 0.4.0
Summary: Common API for Ethereum key operations.
Home-page: https://github.com/ethereum/ethrpc-keys
Author: Piper Merriam
Author-email: pipermerriam@gmail.com
License: MIT
Keywords: ethereum
Platform: UNKNOWN
Classifier: Development Status :: 4 - Beta
Classifier: Intended Audience :: Developers
Classifier: License :: OSI Approved :: MIT License
Classifier: Natural Language :: English
Classifier: Programming Language :: Python :: 3
Classifier: Programming Language :: Python :: 3.6
Classifier: Programming Language :: Python :: 3.7
Classifier: Programming Language :: Python :: 3.8
Classifier: Programming Language :: Python :: 3.9
Classifier: Programming Language :: Python :: 3.10
Provides-Extra: coincurve
Provides-Extra: ethrpc-keys
Provides-Extra: test
Provides-Extra: lint
Provides-Extra: dev
License-File: LICENSE
